funpaper/__init__.py
funpaper/podcast/__init__.py
funpaper/podcast/audio_gen.py
funpaper/podcast/command.py
funpaper/podcast/script.py
funpaper/podcast/templates.py
funpaper-1.0.8.dist-info/METADATA
funpaper-1.0.8.dist-info/WHEEL
funpaper-1.0.8.dist-info/entry_points.txt
funpaper-1.0.8.dist-info/top_level.txt
funpaper-1.0.8.dist-info/RECORD
